steps/Q5/comp2/comp2.v
module comp2(
    output A_gt_B, A_lt_B, A_eq_B, 
    input [1:0] A, B);

    wire tmp1,tmp2,tmp3,tmp4,tmp5, tmp6, tmp7, tmp8;  

    // A = B
    assign tmp1 = A[1] ^~ B[1];  
    assign tmp2 = A[0] ^~ B[0];  
    assign A_eq_B = tmp1 && tmp2;  

    // A < B   
    assign tmp3 = (~A[0]) & (~A[1]) & B[0];  
    assign tmp4 = (~A[1]) & B[1];  
    assign tmp5 = (~A[0]) & B[1] & B[0];  
    assign A_lt_B = tmp3 | tmp4 | tmp5;  

    // A > B   
    assign tmp6 = (~B[0]) & (~B[1]) & A[0];  
    assign tmp7 = (~B[1]) & A[1];  
    assign tmp8 = (~B[0]) & A[1] & A[0];  
    assign A_gt_B = tmp6 | tmp7 | tmp8;  

endmodule

steps/Q5/comp2/comp2_tb.v
`timescale 1ns / 1ps

module comp2_tb();

    reg [1:0] A_TB, B_TB;
    wire gt_TB, lt_TB, eq_TB;

    comp2 UUT (.A_gt_B(gt_TB), .A_lt_B(lt_TB), .A_eq_B(eq_TB), .A(A_TB), .B(B_TB));

    initial begin
        $dumpfile("comp2_tb.vcd");
        $dumpvars(0,comp2_tb);

            A_TB=2'b00; B_TB=2'b00;
        #10 A_TB=2'b00; B_TB=2'b01;
        #10 A_TB=2'b00; B_TB=2'b10;
        #10 A_TB=2'b00; B_TB=2'b11;
        #10 A_TB=2'b01; B_TB=2'b00;
        #10 A_TB=2'b01; B_TB=2'b01;
        #10 A_TB=2'b01; B_TB=2'b10;
        #10 A_TB=2'b01; B_TB=2'b11;
        #10 A_TB=2'b10; B_TB=2'b00;
        #10 A_TB=2'b10; B_TB=2'b01;
        #10 A_TB=2'b10; B_TB=2'b11;
        #10 A_TB=2'b10; B_TB=2'b10;
        #10 A_TB=2'b11; B_TB=2'b01;
        #10 A_TB=2'b11; B_TB=2'b00;
        #10 A_TB=2'b11; B_TB=2'b11;
        #10 A_TB=2'b11; B_TB=2'b11;
    end

endmodule

steps/Q5/comp2/comp2_tb.vcd
$date
	Tue Nov  9 20:46:04 2021
$end
$version
	Icarus Verilog
$end
$timescale
	1ps
$end
$scope module comp2_tb $end
$var wire 1 ! lt_TB $end
$var wire 1 " gt_TB $end
$var wire 1 # eq_TB $end
$var reg 2 $ A_TB [1:0] $end
$var reg 2 % B_TB [1:0] $end
$scope module UUT $end
$var wire 2 & A [1:0] $end
$var wire 1 # A_eq_B $end
$var wire 1 " A_gt_B $end
$var wire 1 ! A_lt_B $end
$var wire 2 ' B [1:0] $end
$var wire 1 ( tmp1 $end
$var wire 1 ) tmp2 $end
$var wire 1 * tmp3 $end
$var wire 1 + tmp4 $end
$var wire 1 , tmp5 $end
$var wire 1 - tmp6 $end
$var wire 1 . tmp7 $end
$var wire 1 / tmp8 $end
$upscope $end
$upscope $end
$enddefinitions $end
#0
$dumpvars
0/
0.
0-
0,
0+
0*
1)
1(
b0 '
b0 &
b0 %
b0 $
1#
0"
0!
$end
#10000
1!
0#
0)
1*
b1 %
b1 '
#20000
0(
1)
0*
1+
b10 %
b10 '
#30000
0)
1*
1,
b11 %
b11 '
#40000
1"
0!
1-
1(
0*
0+
0,
b0 %
b0 '
b1 $
b1 &
#50000
0"
0-
1#
1)
b1 %
b1 '
#60000
1!
0#
0(
0)
1+
b10 %
b10 '
#70000
1)
b11 %
b11 '
#80000
1"
0!
1.
0+
b0 %
b0 '
b10 $
b10 &
#90000
0)
b1 %
b1 '
#100000
0"
1!
1,
0.
1(
b11 %
b11 '
#110000
1#
0!
1)
0,
b10 %
b10 '
#120000
0#
0!
1.
1"
0(
0,
0/
b1 %
b1 '
b11 $
b11 &
#130000
1-
1/
0)
b0 %
b0 '
#140000
0"
0-
0/
1#
0.
1(
1)
b11 %
b11 '
